fastrecord/__init__.py
fastrecord/base.py
fastrecord/cache/__init__.py
fastrecord/cache/base.py
fastrecord/cache/disabled.py
fastrecord/cache/memory_cache.py
fastrecord/cache/redis_cache.py
fastrecord/callbacks.py
fastrecord/concat_python.sh
fastrecord/config.py
fastrecord/decorators/__init__.py
fastrecord/decorators/cache.py
fastrecord/decorators/query_cache.py
fastrecord/middleware/__init__.py
fastrecord/middleware/database.py
fastrecord/query/__init__.py
fastrecord/query/builder.py
fastrecord/query/chain.py
fastrecord/query/scopes.py
fastrecord/relationships/__init__.py
fastrecord/relationships/base.py
fastrecord/relationships/belongs_to.py
fastrecord/relationships/has_many.py
fastrecord/relationships/has_one.py
fastrecord/relationships/polymorphic.py
fastrecord/utils/__init__.py
fastrecord/utils/connection.py
fastrecord/utils/inflector.py
fastrecord/utils/session.py
fastrecord/validation/__init__.py
fastrecord/validation/validator.py
fastrecord/validation/validators/__init__.py
fastrecord/validation/validators/common.py
fastrecord/validation/validators/custom.py
fastrecord/validation/validators/format.py
fastrecord/validation/validators/length.py
fastrecord/validation/validators/presence.py
fastrecord-0.1.1.dist-info/LICENSE.md
fastrecord-0.1.1.dist-info/METADATA
fastrecord-0.1.1.dist-info/WHEEL
fastrecord-0.1.1.dist-info/RECORD
