Metadata-Version: 2.1
Name: fastrecord
Version: 0.1.1
Summary: A Rails-like ORM for FastAPI using SQLModel
Home-page: https://github.com/innovalabs-tech/fastrecord#readme
License: MIT
Keywords: fastapi,orm,database,sqlmodel,rails
Author: Tushar Mangukiya
Author-email: tushar.m@innovalabs.tech
Requires-Python: >=3.9,<4.0
Classifier: License :: OSI Approved :: MIT License
Classifier: Programming Language :: Python :: 3
Classifier: Programming Language :: Python :: 3.9
Classifier: Programming Language :: Python :: 3.10
Classifier: Programming Language :: Python :: 3.11
Classifier: Programming Language :: Python :: 3.12
Classifier: Programming Language :: Python :: 3.13
Requires-Dist: fastapi (>=0.115.5,<0.116.0)
Requires-Dist: inflect (>=7.4.0,<8.0.0)
Requires-Dist: pydantic-settings (>=2.6.1,<3.0.0)
Requires-Dist: redis[hiredis] (>=5.2.0,<6.0.0)
Requires-Dist: sqlmodel (>=0.0.22,<0.0.23)
Project-URL: Repository, https://github.com/innovalabs-tech/fastrecord
